uhppoted/decode.py
uhppoted/encode.py
uhppoted/structs.py
uhppoted/udp.py
uhppoted/uhppote.py
uhppoted-0.8.8.1.dist-info/LICENSE
uhppoted-0.8.8.1.dist-info/METADATA
uhppoted-0.8.8.1.dist-info/WHEEL
uhppoted-0.8.8.1.dist-info/top_level.txt
uhppoted-0.8.8.1.dist-info/RECORD
