Metadata-Version: 2.1
Name: uhppoted
Version: 0.8.8.1
Summary: Python API for the UHPPOTE TCP/IP access controllers
Author-email: uhppoted <uhppoted.development@gmail.com>
Project-URL: Homepage, https://github.com/uhppoted/uhppoted-python
Project-URL: Bug Tracker, https://github.com/uhppoted/uhppoted-python/issues
Classifier: Programming Language :: Python :: 3
Classifier: License :: OSI Approved :: MIT License
Classifier: Operating System :: OS Independent
Requires-Python: >=3.9
License-File: LICENSE
Provides-Extra: dev
Requires-Dist: toml ~=0.10.2 ; extra == 'dev'
Requires-Dist: yapf ~=0.32.0 ; extra == 'dev'
Provides-Extra: test
